compact/__init__.py
compact-0.1.dist-info/METADATA
compact-0.1.dist-info/WHEEL
compact-0.1.dist-info/top_level.txt
compact-0.1.dist-info/RECORD
