Metadata-Version: 2.1
Name: compact
Version: 0.1
Summary: PHP compact for Python
Home-page: http://github.com/robinvandernoord/compact
Author: Robin van der Noord
Author-email: robinvandernoord@gmail.com
License: MIT
Platform: UNKNOWN
